CHANGES.rst
MANIFEST.in
README.rst
setup.py
redis_hash/__init__.py
redis_hash.egg-info/PKG-INFO
redis_hash.egg-info/SOURCES.txt
redis_hash.egg-info/dependency_links.txt
redis_hash.egg-info/top_level.txt