Metadata-Version: 1.1
Name: redis-hash
Version: 1.0.1
Summary: Hash interface for redis-py
Home-page: https://github.com/lamenezes/redis-hash
Author: Luiz Menezes
Author-email: luiz.menezesf@gmail.com
License: MIT
Platform: UNKNOWN
Classifier: Development Status :: 3 - Alpha
Classifier: Intended Audience :: Developers
Classifier: Programming Language :: Python :: 3
Classifier: Programming Language :: Python :: 3.5
